{
  "url": "https://instagram.com/p/DT2BAlGksIR/",
  "video_path": "/Users/bherms/src/japan/data/raw/DT2BAlGksIR/2026-01-23_07-01-03_UTC.mp4",
  "caption": "Japan’s ultimate treasure store — 280,000 items inside!#osaka #handsman",
  "transcript": "This place in Japan is called a paradise for men. 280,000 products in one store. Looks like Odin. Nope, it's a faucet. Looks like sushi. Also a faucet. A kettle. Still a faucet. An Italian imported fountain. $12,000. Here, if you can see it, you can buy it. A giant coconut tree. $10,000. Even the toilet paper comes with a touch and feel test. A 2-meter ice cream cone. Why not? One tiny frog figurine comes in 100-plus designs. Frogtime's Lucky Cat collab are only $5. These look like casual sneakers. Actually steel-toe work shoes. Now I get why they call this place a man's playground. Chainsaws, ropes, axes, every tool you can think of. Lawnmowers, cultivators, and 2,500 kinds of plants at bargain prices. In the disaster supplies section, 5-year shelf-life cookies, 7-year water and rice. And curry you can eat without heating. Japan really thinks of everything. How do we experience ratings?",
  "transcript_segments": [
    {
      "start": 0.0,
      "end": 2.96,
      "text": "This place in Japan is called a paradise for men."
    },
    {
      "start": 3.2,
      "end": 5.72,
      "text": "280,000 products in one store."
    },
    {
      "start": 6.02,
      "end": 6.84,
      "text": "Looks like Odin."
    },
    {
      "start": 7.04,
      "end": 8.58,
      "text": "Nope, it's a faucet."
    },
    {
      "start": 9.02,
      "end": 9.82,
      "text": "Looks like sushi."
    },
    {
      "start": 10.22,
      "end": 11.16,
      "text": "Also a faucet."
    },
    {
      "start": 11.46,
      "end": 11.9,
      "text": "A kettle."
    },
    {
      "start": 12.2,
      "end": 13.02,
      "text": "Still a faucet."
    },
    {
      "start": 13.28,
      "end": 14.6,
      "text": "An Italian imported fountain."
    },
    {
      "start": 15.02,
      "end": 15.82,
      "text": "$12,000."
    },
    {
      "start": 16.4,
      "end": 18.9,
      "text": "Here, if you can see it, you can buy it."
    },
    {
      "start": 18.96,
      "end": 20.14,
      "text": "A giant coconut tree."
    },
    {
      "start": 20.34,
      "end": 21.1,
      "text": "$10,000."
    },
    {
      "start": 21.6,
      "end": 24.28,
      "text": "Even the toilet paper comes with a touch and feel test."
    },
    {
      "start": 24.52,
      "end": 25.92,
      "text": "A 2-meter ice cream cone."
    },
    {
      "start": 26.06,
      "end": 26.78,
      "text": "Why not?"
    },
    {
      "start": 26.78,
      "end": 30.68,
      "text": "One tiny frog figurine comes in 100-plus designs."
    },
    {
      "start": 31.02,
      "end": 33.64,
      "text": "Frogtime's Lucky Cat collab are only $5."
    },
    {
      "start": 34.4,
      "end": 35.96,
      "text": "These look like casual sneakers."
    },
    {
      "start": 36.44,
      "end": 37.94,
      "text": "Actually steel-toe work shoes."
    },
    {
      "start": 38.42,
      "end": 41.02,
      "text": "Now I get why they call this place a man's playground."
    },
    {
      "start": 41.5,
      "end": 45.24,
      "text": "Chainsaws, ropes, axes, every tool you can think of."
    },
    {
      "start": 45.62,
      "end": 50.76,
      "text": "Lawnmowers, cultivators, and 2,500 kinds of plants at bargain prices."
    },
    {
      "start": 51.06,
      "end": 56.12,
      "text": "In the disaster supplies section, 5-year shelf-life cookies, 7-year water and rice."
    },
    {
      "start": 56.12,
      "end": 58.36,
      "text": "And curry you can eat without heating."
    },
    {
      "start": 58.74,
      "end": 60.74,
      "text": "Japan really thinks of everything."
    },
    {
      "start": 61.74,
      "end": 63.14,
      "text": "How do we experience ratings?"
    }
  ],
  "detected_language": "en",
  "onscreen_texts": [
    {
      "text": "|",
      "confidence": 0.929,
      "timestamp": 4.0
    },
    {
      "text": "川E",
      "confidence": 0.592,
      "timestamp": 4.0
    },
    {
      "text": "5409",
      "confidence": 0.949,
      "timestamp": 8.0
    },
    {
      "text": "451",
      "confidence": 0.875,
      "timestamp": 10.0
    },
    {
      "text": "5",
      "confidence": 0.856,
      "timestamp": 10.0
    },
    {
      "text": "heoog",
      "confidence": 0.552,
      "timestamp": 14.0
    },
    {
      "text": "DE",
      "confidence": 0.459,
      "timestamp": 16.0
    },
    {
      "text": "COIFEE",
      "confidence": 0.551,
      "timestamp": 16.0
    },
    {
      "text": "1",
      "confidence": 0.645,
      "timestamp": 22.0
    },
    {
      "text": "IILC",
      "confidence": 0.517,
      "timestamp": 22.0
    },
    {
      "text": "川川",
      "confidence": 0.94,
      "timestamp": 22.0
    },
    {
      "text": "川",
      "confidence": 0.827,
      "timestamp": 24.0
    },
    {
      "text": "50",
      "confidence": 1.0,
      "timestamp": 24.0
    },
    {
      "text": "エリエール",
      "confidence": 0.85,
      "timestamp": 24.0
    },
    {
      "text": "じ",
      "confidence": 0.746,
      "timestamp": 24.0
    },
    {
      "text": "i:na",
      "confidence": 0.612,
      "timestamp": 24.0
    },
    {
      "text": "9",
      "confidence": 0.959,
      "timestamp": 24.0
    },
    {
      "text": "i:na(イーナ",
      "confidence": 0.741,
      "timestamp": 24.0
    },
    {
      "text": "エリエー",
      "confidence": 0.506,
      "timestamp": 24.0
    },
    {
      "text": "昌",
      "confidence": 0.648,
      "timestamp": 24.0
    },
    {
      "text": "四",
      "confidence": 0.699,
      "timestamp": 26.0
    },
    {
      "text": "30",
      "confidence": 0.416,
      "timestamp": 28.0
    },
    {
      "text": "Bの",
      "confidence": 0.639,
      "timestamp": 28.0
    },
    {
      "text": "町",
      "confidence": 0.846,
      "timestamp": 28.0
    },
    {
      "text": "528n",
      "confidence": 0.415,
      "timestamp": 30.0
    },
    {
      "text": "580",
      "confidence": 0.893,
      "timestamp": 30.0
    },
    {
      "text": "T",
      "confidence": 0.96,
      "timestamp": 42.0
    },
    {
      "text": "』",
      "confidence": 0.82,
      "timestamp": 44.0
    },
    {
      "text": "り",
      "confidence": 0.544,
      "timestamp": 44.0
    },
    {
      "text": "OURSE",
      "confidence": 0.836,
      "timestamp": 48.0
    },
    {
      "text": "山",
      "confidence": 0.472,
      "timestamp": 50.0
    },
    {
      "text": "日",
      "confidence": 0.789,
      "timestamp": 50.0
    },
    {
      "text": "Levain」",
      "confidence": 0.868,
      "timestamp": 54.0
    },
    {
      "text": "仏",
      "confidence": 0.855,
      "timestamp": 54.0
    },
    {
      "text": "クッカ",
      "confidence": 0.641,
      "timestamp": 54.0
    },
    {
      "text": "円",
      "confidence": 0.595,
      "timestamp": 54.0
    },
    {
      "text": "548",
      "confidence": 0.991,
      "timestamp": 54.0
    },
    {
      "text": "サクッと広がる",
      "confidence": 0.97,
      "timestamp": 54.0
    },
    {
      "text": "香ばしさ",
      "confidence": 0.981,
      "timestamp": 54.0
    },
    {
      "text": "山しき",
      "confidence": 0.835,
      "timestamp": 54.0
    },
    {
      "text": "ルヴァ",
      "confidence": 0.402,
      "timestamp": 54.0
    },
    {
      "text": "zgeo",
      "confidence": 0.659,
      "timestamp": 56.0
    },
    {
      "text": "20305月",
      "confidence": 0.95,
      "timestamp": 56.0
    },
    {
      "text": "1808",
      "confidence": 0.483,
      "timestamp": 56.0
    },
    {
      "text": "12食入",
      "confidence": 0.994,
      "timestamp": 56.0
    },
    {
      "text": "?",
      "confidence": 0.427,
      "timestamp": 56.0
    },
    {
      "text": "間単調理",
      "confidence": 0.593,
      "timestamp": 56.0
    },
    {
      "text": "保存食",
      "confidence": 0.98,
      "timestamp": 56.0
    },
    {
      "text": "た",
      "confidence": 0.996,
      "timestamp": 58.0
    },
    {
      "text": "野",
      "confidence": 0.991,
      "timestamp": 58.0
    },
    {
      "text": "たつ",
      "confidence": 0.995,
      "timestamp": 58.0
    },
    {
      "text": "Clic",
      "confidence": 0.424,
      "timestamp": 58.0
    },
    {
      "text": "れる",
      "confidence": 1.0,
      "timestamp": 58.0
    },
    {
      "text": "150",
      "confidence": 0.926,
      "timestamp": 58.0
    },
    {
      "text": "1798",
      "confidence": 0.77,
      "timestamp": 58.0
    },
    {
      "text": "0925",
      "confidence": 0.648,
      "timestamp": 58.0
    },
    {
      "text": "〈26972〉",
      "confidence": 0.973,
      "timestamp": 60.0
    },
    {
      "text": "の",
      "confidence": 0.946,
      "timestamp": 60.0
    }
  ]
}